[{"id":1,"name":"Michaela K.","text":"We could not have asked for a better dog sitter than Johnny!","image":"/testimonial-pet-1.jpeg","rating":5},{"id":2,"name":"Yixie L.","text":"We had a pleasant experience leaving our dog with Johnny.","image":"/testimonial-pet-2.jpeg","rating":5},{"id":3,"name":"Alice G.","text":"We had a great experience with Johnny.","image":"/testimonial-pet-3.jpeg","rating":5},{"id":4,"name":"Mark T.","text":"Johnny is an exceptional pet sitter!","image":"/testimonial-pet-2.jpeg","rating":5},{"id":5,"name":"Sarah J.","text":"I was nervous about leaving my senior dog, but Johnny put my mind at ease.","image":"/testimonial-pet-1.jpeg","rating":5}]
